MANIFEST.in
setup.py
Yass.egg-info/PKG-INFO
Yass.egg-info/SOURCES.txt
Yass.egg-info/dependency_links.txt
Yass.egg-info/entry_points.txt
Yass.egg-info/not-zip-safe
Yass.egg-info/requires.txt
Yass.egg-info/top_level.txt
yass/__about__.py
yass/__about__.pyc
yass/__init__.py
yass/__init__.pyc
yass/cli.py
yass/cli.pyc
yass/publisher.py
yass/publisher.pyc
yass/utils.py
yass/utils.pyc
yass/yass.py
yass/yass.pyc
yass/extras/__init__.py
yass/extras/__init__.pyc
yass/extras/htmlcompress.py
yass/extras/htmlcompress.pyc
yass/extras/jade.py
yass/extras/jade.pyc
yass/extras/macros.html
yass/extras/md.py
yass/extras/md.pyc
yass/skel/README.md
yass/skel/yass.yml
yass/skel/data/family.json
yass/skel/pages/about-us.jade
yass/skel/pages/blank.jade
yass/skel/pages/error.jade
yass/skel/pages/index.jade
yass/skel/static/css/style.css
yass/skel/static/img/yass.gif
yass/skel/static/js/app.js
yass/skel/static/vendor/bootstrap/css/bootstrap-theme.css
yass/skel/static/vendor/bootstrap/css/bootstrap-theme.css.map
yass/skel/static/vendor/bootstrap/css/bootstrap-theme.min.css
yass/skel/static/vendor/bootstrap/css/bootstrap-theme.min.css.map
yass/skel/static/vendor/bootstrap/css/bootstrap.css
yass/skel/static/vendor/bootstrap/css/bootstrap.css.map
yass/skel/static/vendor/bootstrap/css/bootstrap.min.css
yass/skel/static/vendor/bootstrap/css/bootstrap.min.css.map
yass/skel/static/vendor/bootstrap/fonts/glyphicons-halflings-regular.eot
yass/skel/static/vendor/bootstrap/fonts/glyphicons-halflings-regular.svg
yass/skel/static/vendor/bootstrap/fonts/glyphicons-halflings-regular.ttf
yass/skel/static/vendor/bootstrap/fonts/glyphicons-halflings-regular.woff
yass/skel/static/vendor/bootstrap/fonts/glyphicons-halflings-regular.woff2
yass/skel/static/vendor/bootstrap/js/bootstrap.js
yass/skel/static/vendor/bootstrap/js/bootstrap.min.js
yass/skel/static/vendor/bootstrap/js/npm.js
yass/skel/static/vendor/font-awesome/css/font-awesome.css
yass/skel/static/vendor/font-awesome/css/font-awesome.min.css
yass/skel/static/vendor/font-awesome/fonts/FontAwesome.otf
yass/skel/static/vendor/font-awesome/fonts/fontawesome-webfont.eot
yass/skel/static/vendor/font-awesome/fonts/fontawesome-webfont.svg
